{
  "project_info": {
    "project_number": "702561533951",
    "firebase_url": "https://sharesep1-db-default-rtdb.firebaseio.com",
    "project_id": "sharesep1-db",
    "storage_bucket": "sharesep1-db.appspot.com"
  },
  "client": [
    {
      "client_info": {
        "mobilesdk_app_id": "1:702561533951:android:66767df79f9a2738a771ca",
        "android_client_info": {
          "package_name": "com.example.sharesep"
        }
      },
      "oauth_client": [
        {
          "client_id": "702561533951-ffibrfqjkq3e5q9l6efgtt1l7otrrv3k.apps.googleusercontent.com",
          "client_type": 3
        }
      ],
      "api_key": [
        {
          "current_key": "AIzaSyDAoSFt41K9-qYAwrnOHS9TwS-NvUyDiSE"
        }
      ],
      "services": {
        "appinvite_service": {
          "other_platform_oauth_client": [
            {
              "client_id": "702561533951-ffibrfqjkq3e5q9l6efgtt1l7otrrv3k.apps.googleusercontent.com",
              "client_type": 3
            }
          ]
        }
      }
    }
  ],
  "configuration_version": "1"
}